[
  {
    "id": 1,
    "Sun": "Bootcamp",
    "timeS":"6.00am",
    "Mon": "Swimming",
    "timeM":"6.00am",
    "Tues": "Walk",
    "timeT":"6.00am",
    "Wed": "Yoga",
    "timeW":"6.00am",
    "Thu": "Cardio",
    "timeTh":"6.00am",
    "Fri": "Running",
    "timeF":"6.00am",
    "Sat": "Spin",
    "timeSa":"6.00am"
  },
  {
    "id": 2,
    "Sun": "Swimming",
    "timeS":"7.00am",
    "Mon": "Bootcamp",
    "timeM":"7.00am",
    "Tues": "Walk",
    "timeT":"7.00am",
    "Wed": "Swimming",
    "timeW":"7.00am",
    "Thu": "Cardio",
    "timeTh":"7.00am",
    "Fri": "Running",
    "timeF":"7.00am",
    "Sat": "Spin",
    "timeSa":"7.00am"
  },
  {
    "id": 3,
    "Sun": "Walk",
    "timeS":"8.00am",
    "Mon": "Walk",
    "timeM":"8.00am",
    "Tues": "Walk",
    "timeT":"8.00am",
    "Wed": "Yoga",
    "timeW":"8.00am",
    "Thu": "Running",
    "timeTh":"8.00am",
    "Fri": "Running",
    "timeF":"8.00am",
    "Sat": "Spin",
    "timeSa":"8.00am"
  },
  {
    "id": 4,
    "Sun": "Yoga",
    "timeS":"9.00am",
    "Mon": "Swimming",
    "timeM":"9.00am",
    "Tues": "Yoga",
    "timeT":"9.00am",
    "Wed": "Yoga",
    "timeW":"9.00am",
    "Thu": "Cardio",
    "timeTh":"9.00am",
    "Fri": "Running",
    "timeF":"9.00am",
    "Sat": "Spin",
    "timeSa":"9.00am"
  },
  {
    "id": 10,
    "Sun": "Cardio",
    "timeS":"3.00pm",
    "Mon": "Swimming",
    "timeM":"3.00pm",
    "Tues": "Cardio",
    "timeT":"3.00pm",
    "Wed": "Yoga",
    "timeW":"3.00pm",
    "Thu": "Cardio",
    "timeTh":"3.00pm",
    "Fri": "Running",
    "timeF":"3.00pm",
    "Sat": "Spin",
    "timeSa":"3.00pm"
  }
]
